{
  "flightNumber": "DL164",
  "flightStatus": "On time | Arrived",
  "departure": {
    "airportCode": "MSP",
    "airportName": "Minneapolis-Saint Paul International Airport, MN, US",
    "date": "2015-05-22",
    "scheduledTime": "9:42 PM  CDT",
    "actualTime": "9:45 PM  CDT",
    "scheduledRunwayTime": "9:57 PM  CDT",
    "actualRunwayTime": "9:56 PM  CDT",
    "terminal": "1",
    "gate": "G6",
    "baggageClaim": null
  },
  "arrival": {
    "airportCode": "AMS",
    "airportName": "Amsterdam Schiphol Airport, NL",
    "date": "2015-05-23",
    "scheduledTime": "1:00 PM  CEST",
    "actualTime": "12:38 PM  CEST",
    "scheduledRunwayTime": "1:08 PM  CEST",
    "actualRunwayTime": "12:29 PM  CEST",
    "terminal": "2",
    "gate": "D43",
    "baggageClaim": null
  },
  "aircraft": {
    "type": "A333",
    "code": null,
    "tailNumber": null
  },
  "scheduledFlightTime": "8h 18m",
  "actualFlightTime": "7h 53m"
}